Expedition/__init__.py
Expedition/dll_wrapper.py
Expedition/enums.py
Expedition/version.py
expedition_python-1.1.3.dist-info/licenses/LICENSE
expedition_python-1.1.3.dist-info/METADATA
expedition_python-1.1.3.dist-info/WHEEL
expedition_python-1.1.3.dist-info/top_level.txt
expedition_python-1.1.3.dist-info/RECORD
