Metadata-Version: 2.4
Name: Expedition-Python
Version: 1.1.3
Summary: Python wrapper for the Expedition DLL
Home-page: https://github.com/TTCMarine/Expedition-Python
Author: Tom Cheney
Author-email: tom@ttcmarine.com
Project-URL: Documentation, https://expedition-python.readthedocs.io
Project-URL: Source, https://github.com/TTCMarine/Expedition-Python
Project-URL: Bug Tracker, https://github.com/TTCMarine/Expedition-Python/issues
Classifier: Development Status :: 5 - Production/Stable
Classifier: Intended Audience :: Developers
Classifier: License :: OSI Approved :: MIT License
Classifier: Programming Language :: Python :: 3.12
License-File: LICENSE
Dynamic: author
Dynamic: author-email
Dynamic: classifier
Dynamic: description
Dynamic: description-content-type
Dynamic: home-page
Dynamic: license-file
Dynamic: project-url
Dynamic: summary
